Workbook

Sheet Lecture
A1: Information | B1: Portée
A2: Projet | B2: Spity, projet solo sur un an déclaré par Dorian. Mois exacts non fournis.
A3: Chronologie | B3: Dates Git : étapes enregistrées, pas relevé exhaustif d’activité.
A4: Linear | B4: Relevé du 14/09/2026, non actualisé. Décompte non pondéré.
A5: Cadrage | B5: Charges et montants estimés du diaporama B1 ; aucun consommé réel.
A6: Navigation | B6: Mesures locales du 15/09, un passage par parcours ; aucune mesure de production.
A7: Retours | B7: Personas et retours simulés pour l’exercice ; pas d’entretiens réalisés.
A8: Formules | B8: Recalculées par LibreOffice ; les sources sont conservées dans le kit.

Sheet Chronologie
A1: Date Git | B1: Étape | C1: Révision | D1: Source
A2: 2026-01-24 | B2: Fondations Next.js et Drizzle | C2: c2783de7f21a896179d9a6cf83cf427e71acd89d | D2: preuves/historique-git.txt
A3: 2026-05-04 | B3: Authentification | C3: f92a86d00e48a9906719483bb21c002397b71df4 | D3: preuves/historique-git.txt
A4: 2026-05-04 | B4: Profils et onboarding | C4: 84d85c9c47cf4e9e760c574fc2d7c5dc697e94c9 | D4: preuves/historique-git.txt
A5: 2026-05-05 | B5: Répertoire des lieux | C5: 97b425b92a9475eeee153dd42efc463433a9e7f8 | D5: preuves/historique-git.txt
A6: 2026-07-20 | B6: Matching et événements | C6: aa5079c26e0904245a3470c8149ec9f7404430f1 | D6: preuves/historique-git.txt
A7: 2026-07-20 | B7: Recette sur build compilé | C7: 689e59dccf15dc611dbddccea9cf81ccc187c40c | D7: preuves/historique-git.txt
A8: 2026-07-28 | B8: Commentaires du feed | C8: 6809b3ed0a1ec93e499bffc06d8ef9913468abe7 | D8: preuves/historique-git.txt
A9: 2026-08-13 | B9: Maintenance des dépendances | C9: f892c31184be8ac889cb912305d15ca3b6394f15 | D9: preuves/historique-git.txt
A10: 2026-08-13 | B10: Supervision | C10: 95c01f79d176c1694447d68f43573138b732a78a | D10: preuves/historique-git.txt
A11: 2026-09-09 | B11: Médias sécurisés | C11: bafa5992bb6f9fd49a0873a051285a5afd4660b9 | D11: preuves/historique-git.txt
A12: 2026-09-09 | B12: Administration | C12: 62937d584b74420e1071a5814c78c311cfc07511 | D12: preuves/historique-git.txt
... A17: 2026-09-15 | B17: Fusion de la PR 35 | C17: 872db197b3e6bf3d053b698829c41674ae42a836 | D17: preuves/historique-git.txt

Sheet Linear
A1: ID | B1: Statut | C1: Priorité | D1: Intitulé | E1: URL
A2: SPI-5 | B2: Canceled | C2: Urgent | D2: SPITY-001: Prisma schema User + Club | E2: https://linear.app/spitywa/issue/SPI-5/spity-001-prisma-schema-user-club
A3: SPI-6 | B3: Todo | C3: High | D3: SPITY-002: JWT auth grimpeur/club | E3: https://linear.app/spitywa/issue/SPI-6/spity-002-jwt-auth-grimpeurclub
A4: SPI-7 | B4: Done | C4: High | D4: SPITY-003: Login/register pages | E4: https://linear.app/spitywa/issue/SPI-7/spity-003-loginregister-pages
A5: SPI-8 | B5: Done | C5: Urgent | D5: SPITY-004: Docker compose Next+MariaDB+phpMyAdmin | E5: https://linear.app/spitywa/issue/SPI-8/spity-004-docker-compose-nextmariadbphpmyadmin
A6: SPI-9 | B6: Done | C6: Urgent | D6: SPITY-005: Drizzle schema initial | E6: https://linear.app/spitywa/issue/SPI-9/spity-005-drizzle-schema-initial
A7: SPI-10 | B7: Done | C7: Medium | D7: SPITY-006: GitHub Actions CI/CD | E7: https://linear.app/spitywa/issue/SPI-10/spity-006-github-actions-cicd
A8: SPI-11 | B8: Todo | C8: High | D8: SPITY-007: CRUD profil grimpeur (disciplines, niveaux, matos) | E8: https://linear.app/spitywa/issue/SPI-11/spity-007-crud-profil-grimpeur-disciplines-niveaux-matos
A9: SPI-12 | B9: Backlog | C9: Medium | D9: SPITY-008: CRUD profil club (coachs, validation) | E9: https://linear.app/spitywa/issue/SPI-12/spity-008-crud-profil-club-coachs-validation
A10: SPI-13 | B10: Done | C10: High | D10: SPITY-009: Page profil grimpeur + édition | E10: https://linear.app/spitywa/issue/SPI-13/spity-009-page-profil-grimpeur-edition
A11: SPI-14 | B11: Done | C11: Medium | D11: SPITY-010: Page profil club | E11: https://linear.app/spitywa/issue/SPI-14/spity-010-page-profil-club
A12: SPI-15 | B12: Todo | C12: High | D12: SPITY-011: CRUD Post (texte, media, tags, cotation) | E12: https://linear.app/spitywa/issue/SPI-15/spity-011-crud-post-texte-media-tags-cotation
... A26: SPI-29 | B26: Done | C26: Low | D26: SPITY-025: Sécurité OWASP + accessibilité RGAA | E26: https://linear.app/spitywa/issue/SPI-29/spity-025-securite-owasp-accessibilite-rgaa

Sheet Indicateurs
A1: Indicateur | B1: Valeur | C1: Unité / limite
A2: Tickets observés | B2: =COUNTA(Linear!A2:A26) -> 25 | C2: Relevé du 14/09
A3: Annulés | B3: =COUNTIF(Linear!B2:B26,"Canceled") -> 1 | C3: Exclus du dénominateur
A4: Non annulés | B4: =B2-B3 -> 24 | C4: Tickets, sans pondération
A5: Terminés | B5: =COUNTIF(Linear!B2:B26,"Done") -> 12 | C5: Statut historique
A6: Part terminée | B6: =IF(B4=0,"",B5/B4) -> 0.5 | C6: Décompte ; ne mesure pas la livraison du produit
A7: Médiane avant | B7: =MEDIAN(Navigation!B2:B6) -> 10220 | C7: ms ; protocole local
A8: Médiane après | B8: =MEDIAN(Navigation!C2:C6) -> 748 | C8: ms ; protocole local

Sheet Cadrage
A1: Lot / poste | B1: j-h estimés | C1: Taux €/j-h | D1: Montant € | E1: Nature
A2: Cadrage, UX, backlog | B2: 8 | C2: 450 | D2: =B2*C2 -> 3600 | E2: Estimation B1
A3: Setup technique | B3: 6 | C3: 450 | D3: =B3*C3 -> 2700 | E3: Estimation B1
A4: Auth et sécurité de base | B4: 10 | C4: 450 | D4: =B4*C4 -> 4500 | E4: Estimation B1
A5: Profils grimpeur/club | B5: 9 | C5: 450 | D5: =B5*C5 -> 4050 | E5: Estimation B1
A6: Feed social | B6: 12 | C6: 450 | D6: =B6*C6 -> 5400 | E6: Estimation B1
A7: Répertoire géolocalisé | B7: 10 | C7: 450 | D7: =B7*C7 -> 4500 | E7: Estimation B1
A8: Topos collaboratifs | B8: 9 | C8: 450 | D8: =B8*C8 -> 4050 | E8: Estimation B1
A9: Événements clubs | B9: 8 | C9: 450 | D9: =B9*C9 -> 3600 | E9: Estimation B1
A10: Tests, accessibilité, documentation | B10: 10 | C10: 450 | D10: =B10*C10 -> 4500 | E10: Estimation B1
A11: Total développement | B11: =SUM(B2:B10) -> 82 | D11: =SUM(D2:D10) -> 36900 | E11: Prévision, pas dépense réelle
A12: Infrastructure annuelle | D12: 1200 | E12: Estimation B1
A13: Médias et cartographie | D13: 900 | E13: Estimation B1
A14: Nom de domaine et email | D14: 250 | E14: Estimation B1
A15: Sécurité et conformité | D15: 2000 | E15: Estimation B1
A16: Tests et recette | D16: 3000 | E16: Estimation B1
A17: TOTAL B1 | D17: =SUM(D11:D16) -> 44250 | E17: Aucune convention HT ajoutée
A18: Temps réellement consommé | E18: Non fourni : cellule vide, pas zéro
A19: Coûts réellement consommés | E19: Non fournis : aucun écart calculé

Sheet Navigation
A1: Parcours | B1: Avant (ms) | C1: Après (ms) | D1: Écart (ms) | E1: Protocole
A2: Partenaires | B2: 11041 | C2: 1123 | D2: =C2-B2 -> -9918 | E2: Build de production local ; Chromium, CPU ×4, latence 100 ms, débit 1 000 000 octets/s, un passage par parcours. Aucune mesure de performance en production.
A3: Événements | B3: 9917 | C3: 763 | D3: =C3-B3 -> -9154 | E3: Build de production local ; Chromium, CPU ×4, latence 100 ms, débit 1 000 000 octets/s, un passage par parcours. Aucune mesure de performance en production.
A4: Demandes | B4: 10220 | C4: 550 | D4: =C4-B4 -> -9670 | E4: Build de production local ; Chromium, CPU ×4, latence 100 ms, débit 1 000 000 octets/s, un passage par parcours. Aucune mesure de performance en production.
A5: Profil | B5: 10363 | C5: 748 | D5: =C5-B5 -> -9615 | E5: Build de production local ; Chromium, CPU ×4, latence 100 ms, débit 1 000 000 octets/s, un passage par parcours. Aucune mesure de performance en production.
A6: Feed | B6: 8660 | C6: 494 | D6: =C6-B6 -> -8166 | E6: Build de production local ; Chromium, CPU ×4, latence 100 ms, débit 1 000 000 octets/s, un passage par parcours. Aucune mesure de performance en production.

Sheet Retours SIMULES
A1: ID | B1: Persona fictif | C1: Retour inventé | D1: Réponse pédagogique | E1: Critère | F1: Réalisation réelle
A2: SIM-01 | B2: Grimpeur (persona fictif) | C2: Je veux filtrer les partenaires selon la discipline que je pratique et comprendre l’état de ma demande. | D2: Montrer les filtres et les états ; vérifier la cohérence du niveau avec la discipline. | E2: Résultats cohérents et statut de demande lisible. | F2: 363f681
A3: SIM-02 | B3: Responsable de club (persona fictif) | C3: Je dois retrouver les inscrits et savoir s’il reste des places pour ma sortie. | D3: Présenter la capacité et la liste des participants avec une session club. | E3: Liste autorisée, inscription confirmée et capacité respectée. | F3: 363f681
A4: SIM-03 | B4: Grimpeur (persona fictif) | C4: Après un clic dans le menu, je veux savoir que ma navigation est en cours. | D4: Montrer l’indicateur d’attente et la correction du fond décoratif. | E4: Attente visible puis disparition à l’arrivée sur la page. | F4: 83e4c29

Sheet Suivi SIMULE
A1: Indicateur | B1: Valeur | C1: Nature
A2: PÉRIMÈTRE | B2: SIMULATION | C2: Exemple de suivi annuel ; aucun consommé réel
A3: Charge initiale | B3: 82 | C3: j-h ; référence B1
A4: Consommé simulé | B4: 58 | C4: j-h ; hypothèse pédagogique
A5: Reste à faire simulé | B5: 28 | C5: j-h ; hypothèse pédagogique
A6: Prévision | B6: =B4+B5 -> 86 | C6: j-h
A7: Taux valorisé | B7: 450 | C7: €/j-h ; estimation B1
A8: Autres postes | B8: 7350 | C8: € ; estimation B1
A9: Budget initial | B9: =B3*B7+B8 -> 44250 | C9: €
A10: Prévision coût | B10: =B6*B7+B8 -> 46050 | C10: €
A11: Écart | B11: =B10-B9 -> 1800 | C11: €
A12: Écart relatif | B12: =B11/B9 -> 0.040677966 | C12: Proportion
A13: Livraison initiale | B13: 11 | C13: Mois relatif simulé
A14: Livraison révisée | B14: 12 | C14: Mois relatif simulé
A15: Décalage | B15: =B14-B13 -> 1 | C15: Mois
A16: Capacité mensuelle hypothétique | B16: 10 | C16: j-h
A17: Charge prochaine période | B17: 12 | C17: j-h
A18: Taux de charge | B18: =B17/B16 -> 1.2 | C18: Proportion ; alerte > 1
